{
    "Шаблон ожидания wait для текста": {
        "prefix": [
            "w"
        ],
        "body": [
            "wait \"${1:Text}\""
        ],
        "description": "Подставляет шаблонную конструкцию ожидания wait для поиска текста на экране"
    },
    "Шаблон ожидания wait для изображения": {
        "prefix": [
            "wi"
        ],
        "body": [
            "wait img \"${1:IMG path}\""
        ],
        "description": "Подставляет шаблонную конструкцию ожидания wait для поиска изображения на экране"
    },
    "Шаблон ожидания wait для текста с параметром timeout": {
        "prefix": [
            "wt"
        ],
        "body": [
            "wait \"${1:Text}\" timeout ${2:60}s"
        ],
        "description": "Подставляет шаблонную конструкцию ожидания wait для поиска текста на экране с параметром timeout"
    },
    "Шаблон ожидания wait для изображения с параметром timeout": {
        "prefix": [
            "wit"
        ],
        "body": [
            "wait img \"${1:IMG path}\" timeout ${2:60}s"
        ],
        "description": "Подставляет шаблонную конструкцию ожидания wait для поиска изображения на экране с параметром timeout"
    }
}